gitbooster/__init__.py
gitbooster/gitbooster.py
tests/__init__.py
tests/test_gitbooster.py
GitBooster-1.0.0.dist-info/LICENSE
GitBooster-1.0.0.dist-info/METADATA
GitBooster-1.0.0.dist-info/WHEEL
GitBooster-1.0.0.dist-info/entry_points.txt
GitBooster-1.0.0.dist-info/top_level.txt
GitBooster-1.0.0.dist-info/RECORD
