Metadata-Version: 2.1
Name: GitBooster
Version: 1.0.0
Summary: GitBooster:  Boosts your GitHub stats with automated, scheduled commits to keep your profile active.
Home-page: https://github.com/ElNiak/GitBooster
Author: ElNiak
Author-email: your.email@example.com
Classifier: Programming Language :: Python :: 3
Classifier: License :: OSI Approved :: MIT License
Classifier: Operating System :: OS Independent
Requires-Python: >=3.6
License-File: LICENSE
Requires-Dist: setuptools
Requires-Dist: GitPython
Requires-Dist: python-crontab
